myprox/__init__.py
myprox/config.py
myprox/myproxapi.py
myprox/proxapi.py
myprox/setupenv.py
myprox/webapp.py
myprox/templates/base.html
myprox/templates/edit.html
myprox/templates/index.html
myprox/templates/login.html
myprox/templates/manage.html
myprox/templates/myprox.conf
myprox/templates/part_header.html
myprox/webroot/static/favicon.ico
myprox/webroot/static/logo.png
myprox/webroot/static/logo.svg
myprox/webroot/static/styles.css
myprox-1.0.0.dist-info/licenses/LICENSE
myprox-1.0.0.dist-info/METADATA
myprox-1.0.0.dist-info/WHEEL
myprox-1.0.0.dist-info/entry_points.txt
myprox-1.0.0.dist-info/top_level.txt
myprox-1.0.0.dist-info/RECORD
