Metadata-Version: 2.4
Name: MyProx
Version: 1.0.0
Summary: simple web frontend for Proxmox VE users
Home-page: https://www.github.com/towalink/myprox
Author: Dirk Henrici
Author-email: pypi.myprox@henrici.name
Project-URL: Project homepage, https://www.henrici.name/projects/myprox.html
Project-URL: Repository, https://www.github.com/towalink/myprox
Project-URL: Documentation, https://www.github.com/towalink/myprox
Keywords: Proxmox frontend gui
Classifier: Programming Language :: Python
Classifier: Programming Language :: Python :: 3
Classifier: Operating System :: POSIX :: Linux
Classifier: Intended Audience :: End Users/Desktop
Classifier: Intended Audience :: System Administrators
Classifier: Intended Audience :: Information Technology
Classifier: Topic :: System :: Systems Administration
Classifier: Framework :: CherryPy
Requires-Python: >=3.6
License-File: LICENSE
Requires-Dist: cherrypy
Requires-Dist: requests
Requires-Dist: jinja2
Requires-Dist: proxmoxer
Dynamic: author
Dynamic: author-email
Dynamic: classifier
Dynamic: description
Dynamic: description-content-type
Dynamic: home-page
Dynamic: keywords
Dynamic: license-file
Dynamic: project-url
Dynamic: requires-dist
Dynamic: requires-python
Dynamic: summary
